{
  "config": {
    "step": {
      "user": {
        "title": "Eco-Home Login",
        "description": "Enter your Eco-Home app credentials",
        "data": {
          "email": "Email",
          "password": "Password"
        }
      },
      "device": {
        "title": "Select Device",
        "description": "Choose the pool heat pump to integrate",
        "data": {
          "device_code": "Device"
        }
      }
    },
    "error": {
      "invalid_auth": "Invalid email or password",
      "cannot_connect": "Cannot connect to Eco-Home cloud",
      "no_devices": "No devices found on this account"
    },
    "abort": {
      "already_configured": "Device already configured"
    }
  },
  "options": {
    "step": {
      "init": {
        "title": "Options",
        "data": {
          "scan_interval": "Polling interval (seconds)"
        }
      }
    }
  }
}
